localenv/__init__.py
localenv/_modidx.py
localenv/envs.py
localenv-0.0.2.dist-info/LICENSE
localenv-0.0.2.dist-info/METADATA
localenv-0.0.2.dist-info/WHEEL
localenv-0.0.2.dist-info/entry_points.txt
localenv-0.0.2.dist-info/top_level.txt
localenv-0.0.2.dist-info/RECORD
